setup.py
FBlevi/Automation1.py
FBlevi/CreateAccount.py
FBlevi/Friend.py
FBlevi/GetInfo.py
FBlevi/GetToken.py
FBlevi/Login.py
FBlevi/Privacy.py
FBlevi/Setting.py
FBlevi/Tools.py
FBlevi/__init__.py
FBlevi.egg-info/PKG-INFO
FBlevi.egg-info/SOURCES.txt
FBlevi.egg-info/dependency_links.txt
FBlevi.egg-info/top_level.txt