Metadata-Version: 2.1
Name: FBlevi
Version: 0.1
Summary: face tools
Home-page: UNKNOWN
Author: levi tools
License: UNKNOWN
Platform: UNKNOWN
Classifier: Programming Language :: Python :: 3
Classifier: Operating System :: OS Independent
Classifier: License :: OSI Approved :: MIT License
